whisper_ssh/__init__.py
whisper_ssh/__main__.py
whisper_ssh/cli.py
whisper_ssh/config.py
whisper_ssh/core.py
whisper_ssh-1.1.0.dist-info/licenses/LICENSE
whisper_ssh-1.1.0.dist-info/METADATA
whisper_ssh-1.1.0.dist-info/WHEEL
whisper_ssh-1.1.0.dist-info/entry_points.txt
whisper_ssh-1.1.0.dist-info/top_level.txt
whisper_ssh-1.1.0.dist-info/RECORD
