Metadata-Version: 2.4
Name: whisper-ssh
Version: 1.1.0
Summary: Whisper messages to remote Linux machines via SSH
Home-page: https://github.com/JdMasuta/whisper-ssh
Author: Josh Meesey
Maintainer: Josh Meesey
License: MIT License
Project-URL: Homepage, https://github.com/JdMasuta/whisper-ssh
Project-URL: Documentation, https://github.com/JdMasuta/whisper-ssh#readme
Project-URL: Repository, https://github.com/JdMasuta/whisper-ssh.git
Project-URL: Bug Tracker, https://github.com/JdMasuta/whisper-ssh/issues
Project-URL: Changelog, https://github.com/JdMasuta/whisper-ssh/blob/main/CHANGELOG.md
Keywords: ssh,notification,remote,desktop,linux,ubuntu,notify-send,whisper
Platform: any
Classifier: Development Status :: 4 - Beta
Classifier: Intended Audience :: System Administrators
Classifier: Intended Audience :: Developers
Classifier: Topic :: System :: Networking
Classifier: Topic :: System :: Systems Administration
Classifier: Topic :: Communications
Classifier: License :: OSI Approved :: MIT License
Classifier: Programming Language :: Python :: 3
Classifier: Programming Language :: Python :: 3.7
Classifier: Programming Language :: Python :: 3.8
Classifier: Programming Language :: Python :: 3.9
Classifier: Programming Language :: Python :: 3.10
Classifier: Programming Language :: Python :: 3.11
Classifier: Programming Language :: Python :: 3.12
Classifier: Operating System :: OS Independent
Classifier: Environment :: Console
Requires-Python: >=3.7
License-File: LICENSE
Requires-Dist: fabric>=3.0.0
Requires-Dist: questionary>=2.0.0
Requires-Dist: rich>=13.0.0
Requires-Dist: validators>=0.20.0
Provides-Extra: dev
Requires-Dist: pytest>=6.0; extra == "dev"
Requires-Dist: pytest-cov>=2.0; extra == "dev"
Requires-Dist: black>=22.0; extra == "dev"
Requires-Dist: flake8>=4.0; extra == "dev"
Requires-Dist: mypy>=0.910; extra == "dev"
Requires-Dist: pre-commit>=2.15; extra == "dev"
Requires-Dist: twine>=4.0; extra == "dev"
Requires-Dist: build>=0.8; extra == "dev"
Provides-Extra: test
Requires-Dist: pytest>=6.0; extra == "test"
Requires-Dist: pytest-cov>=2.0; extra == "test"
Requires-Dist: pytest-mock>=3.0; extra == "test"
Dynamic: home-page
Dynamic: license-file
Dynamic: platform
Dynamic: requires-python
